jknife/__init__.py
jknife/logging.py
jknife/commands/__init__.py
jknife/commands/jknife.py
jknife/db/__init__.py
jknife/db/models/__init__.py
jknife/db/models/mongo/__init__.py
jknife/db/models/mongo/network.py
jknife/db/models/mongo/personnel_info.py
jknife/db/models/mongo/settings.py
jknife/db/models/mongo/token.py
jknife/db/models/mongo/users.py
jknife/db/models/rdbms/__init__.py
jknife/db/models/rdbms/network.py
jknife/db/models/rdbms/personnel_info.py
jknife/db/models/rdbms/settings.py
jknife/db/models/rdbms/token.py
jknife/db/models/rdbms/users.py
jknife/dependencies/__init__.py
jknife/dependencies/token.py
jknife/dependencies/users.py
jknife/views/__init__.py
jknife/views/error_message.py
jknife/views/personnel_info.py
jknife/views/tokens.py
jknife/views/users.py
jknife-0.0.13.dist-info/METADATA
jknife-0.0.13.dist-info/WHEEL
jknife-0.0.13.dist-info/entry_points.txt
jknife-0.0.13.dist-info/licenses/LICENSE
jknife-0.0.13.dist-info/RECORD
