Metadata-Version: 2.4
Name: jknife
Version: 0.0.13
Summary: Custom FastAPI for luna-negra
Author: luna-negra
License-Expression: MIT
License-File: LICENSE
Keywords: Backend,Customised,FastAPI,Python,pypi
Classifier: Operating System :: OS Independent
Classifier: Programming Language :: Python :: 3
Requires-Dist: blinker>=1.9.0
Requires-Dist: fastapi[standard]<0.120.0,>=0.119.1
Requires-Dist: mongoengine
Requires-Dist: pycountry>=24.6.1
Requires-Dist: pyjwt>=2.10.1
Requires-Dist: redis>=6.4.0
Requires-Dist: sqlmodel>=0.0.24
